[
  {
    "id": "TANG_CENTRAL",
    "name": "大唐中央",
    "description": "虽然开元盛世的余晖尚在，但繁荣之下危机四伏。玄宗晚年倦勤，朝政渐堕。",
    "tags": ["Empire", "Central_Plains", "Declining"],
    "properties": {
      "nominal_ruler": "USER_LI_LONGJI",
      "actual_ruler": "USER_YANG_GUOZHONG",
      "prestige": 85.5,
      "finance": 1250000.0,
      "primary_ethnicity": "汉",
      "map_color": [0.2, 0.6, 0.4, 1.0],
      "capital": "CHANG_AN",
      "provinces": ["chang_an", "luo_yang", "yang_zhou", "su_zhou"]
    }
  },
  {
    "id": "TUBO_KHANATE",
    "name": "吐蕃",
    "description": "高原上的雄狮，时刻觊觎着河西走廊与安西四镇。",
    "tags": ["Foreign", "Plateau", "Aggressive"],
    "property": {
      "nominal_ruler": "USER_CHIDE_ZUZAN",
      "actual_ruler": "USER_CHIDE_ZUZAN",
      "prestige": 75.0,
      "finance": 300000.0,
      "primary_ethnicity": "吐蕃",
      "map_color": [0.7, 0.4, 0.2, 1.0],
      "capital": "LHA_SA",
      "provinces": ["sha_zhou", "liang_zhou"]
    }
  }
]